{
  "schema_version": "2.1",
  "perspective": "business",
  "generated_at": "1970-01-01T00:00:00Z",
  "confidence": "example",
  "entities": [
    {
      "hierarchy": "BD",
      "id": "001",
      "full_id": "BD-EXAMPLE",
      "alias": "ExampleBusinessDomain",
      "name": "示例业务域",
      "description": "仅用于演示业务视角数据结构（示例）。",
      "strategic_classification": "supporting_domain",
      "children": ["BSD-EXAMPLE"],
      "evidence_chain": [],
      "cross_references": { "technical": [], "product": [], "business": [], "data": [] }
    },

    {
      "hierarchy": "BSD",
      "id": "001",
      "full_id": "BSD-EXAMPLE",
      "alias": "ExampleBusinessSubdomain",
      "name": "示例业务子域",
      "description": "仅用于演示业务视角数据结构（示例）。",
      "parent_id": "BD-EXAMPLE",
      "bounded_contexts": ["BC-EXAMPLE"],
      "evidence_chain": [],
      "cross_references": { "technical": [], "product": [], "business": [], "data": [] }
    },

    {
      "hierarchy": "BC",
      "id": "001",
      "full_id": "BC-EXAMPLE",
      "alias": "ExampleBoundedContext",
      "name": "示例限界上下文",
      "description": "仅用于演示业务视角数据结构（示例）。",
      "parent_id": "BSD-EXAMPLE",
      "implemented_by_app_id": "APP-EXAMPLE",
      "aggregates": ["AGG-EXAMPLE"],
      "ubiquitous_language": {
        "术语A": "示例定义A",
        "术语B": "示例定义B"
      },
      "evidence_chain": [],
      "cross_references": { "technical": [], "product": [], "business": [], "data": [] }
    },

    {
      "hierarchy": "AGG",
      "id": "001",
      "full_id": "AGG-EXAMPLE",
      "alias": "ExampleAggregate",
      "name": "示例聚合",
      "description": "仅用于演示业务视角数据结构（示例）。",
      "parent_id": "BC-EXAMPLE",
      "root_entity": "ExampleRoot",
      "entities": ["ExampleEntityA", "ExampleEntityB"],
      "invariants": [
        "示例不变量A",
        "示例不变量B"
      ],
      "persisted_as_entity_ids": ["ENT-EXAMPLE"],
      "implemented_by_service_ids": ["MS-EXAMPLE"],
      "abilities": ["AB-EXAMPLE"],
      "evidence_chain": [],
      "cross_references": { "technical": ["MS-EXAMPLE"], "product": [], "business": ["BC-EXAMPLE"], "data": ["ENT-EXAMPLE"] }
    },

    {
      "hierarchy": "AB",
      "id": "001",
      "full_id": "AB-EXAMPLE",
      "alias": "ExampleAbility",
      "name": "示例能力",
      "description": "仅用于演示业务视角数据结构（示例）。",
      "parent_id": "AGG-EXAMPLE",
      "capability": "示例能力描述",
      "apis": [
        { "id": "API-EXAMPLE-001", "method": "Example.create", "description": "示例：创建" }
      ],
      "evidence_chain": [],
      "cross_references": { "technical": ["MS-EXAMPLE"], "product": [], "business": ["AGG-EXAMPLE"], "data": [] }
    }
  ],
  "metadata": {
    "total_business_domains": 1,
    "total_business_subdomains": 1,
    "total_bounded_contexts": 1,
    "total_aggregates": 1,
    "total_abilities": 1,
    "total_entities": 5,
    "extraction_basis": "示例数据（非从代码/文档提取）。",
    "schema_notes": "schema 2.1：entities 扁平数组，hierarchy 区分层级；各层字段形状以本示例为演示用途。",
    "changes_from_previous": "已裁剪为仅保留示例数据。"
  }
}
